mysql_operator/__init__.py
mysql_operator/backup_operator.py
mysql_operator/cleanup_operator.py
mysql_operator/command_line.py
mysql_operator/migrate_operator.py
mysql_operator-1.0.0.dist-info/METADATA
mysql_operator-1.0.0.dist-info/WHEEL
mysql_operator-1.0.0.dist-info/entry_points.txt
mysql_operator-1.0.0.dist-info/top_level.txt
mysql_operator-1.0.0.dist-info/RECORD
