Metadata-Version: 2.1
Name: mysql-operator
Version: 1.0.0
Summary: A tool for backup/cleanup/migrate mysql
Home-page: https://github.com/chienfeng0719/mysql-operator
Author: Jimmy Yeh
Author-email: chienfeng0719@hotmail.com
License: UNKNOWN
Platform: UNKNOWN
Classifier: Programming Language :: Python :: 3
Classifier: License :: OSI Approved :: MIT License
Classifier: Operating System :: OS Independent
Requires-Python: >=3.6
